{
  "best_global_step": null,
  "best_metric": null,
  "best_model_checkpoint": null,
  "epoch": 2.5806451612903225,
  "eval_steps": 500,
  "global_step": 400,
  "is_hyper_param_search": false,
  "is_local_process_zero": true,
  "is_world_process_zero": true,
  "log_history": [
    {
      "epoch": 0.3225806451612903,
      "grad_norm": NaN,
      "learning_rate": 4.473118279569893e-05,
      "loss": 23.1169677734375,
      "step": 50
    },
    {
      "epoch": 0.6451612903225806,
      "grad_norm": NaN,
      "learning_rate": 3.935483870967742e-05,
      "loss": 0.0,
      "step": 100
    },
    {
      "epoch": 0.967741935483871,
      "grad_norm": NaN,
      "learning_rate": 3.3978494623655916e-05,
      "loss": 0.0,
      "step": 150
    },
    {
      "epoch": 1.2903225806451613,
      "grad_norm": NaN,
      "learning_rate": 2.860215053763441e-05,
      "loss": 0.0,
      "step": 200
    },
    {
      "epoch": 1.6129032258064515,
      "grad_norm": NaN,
      "learning_rate": 2.3225806451612906e-05,
      "loss": 0.0,
      "step": 250
    },
    {
      "epoch": 1.935483870967742,
      "grad_norm": NaN,
      "learning_rate": 1.78494623655914e-05,
      "loss": 0.0,
      "step": 300
    },
    {
      "epoch": 2.258064516129032,
      "grad_norm": NaN,
      "learning_rate": 1.2473118279569892e-05,
      "loss": 0.0,
      "step": 350
    },
    {
      "epoch": 2.5806451612903225,
      "grad_norm": NaN,
      "learning_rate": 7.096774193548387e-06,
      "loss": 0.0,
      "step": 400
    }
  ],
  "logging_steps": 50,
  "max_steps": 465,
  "num_input_tokens_seen": 0,
  "num_train_epochs": 3,
  "save_steps": 200,
  "stateful_callbacks": {
    "TrainerControl": {
      "args": {
        "should_epoch_stop": false,
        "should_evaluate": false,
        "should_log": false,
        "should_save": true,
        "should_training_stop": false
      },
      "attributes": {}
    }
  },
  "total_flos": 211612895470080.0,
  "train_batch_size": 16,
  "trial_name": null,
  "trial_params": null
}
